poma_integrations/__init__.py
poma_integrations/langchain_poma.py
poma_integrations/llamaindex_poma.py
poma_integrations/version.py
poma_integrations-0.1.1.dist-info/licenses/LICENSE
poma_integrations-0.1.1.dist-info/METADATA
poma_integrations-0.1.1.dist-info/PKG-INFO 2
poma_integrations-0.1.1.dist-info/SOURCES 2.txt
poma_integrations-0.1.1.dist-info/WHEEL
poma_integrations-0.1.1.dist-info/dependency_links 2.txt
poma_integrations-0.1.1.dist-info/requires 2.txt
poma_integrations-0.1.1.dist-info/top_level 2.txt
poma_integrations-0.1.1.dist-info/top_level.txt
poma_integrations-0.1.1.dist-info/RECORD
