Metadata-Version: 2.4
Name: poma-integrations
Version: 0.1.1
Summary: POMA Integrations for Langchain and LlamaIndex
Author-email: "TIGON S.L.U." <info@poma.science>
License-Expression: MPL-2.0
Requires-Python: >=3.10
License-File: LICENSE
Requires-Dist: poma-chunker
Requires-Dist: doc2poma
Requires-Dist: poma-senter
Requires-Dist: langchain
Requires-Dist: langchain-community
Requires-Dist: llama_index
Requires-Dist: pydantic
Dynamic: license-file
